cloud_pipelines/components/__init__.py
cloud_pipelines/components/_airflow_op.py
cloud_pipelines/components/_component_store.py
cloud_pipelines/components/_components.py
cloud_pipelines/components/_data_passing.py
cloud_pipelines/components/_dynamic.py
cloud_pipelines/components/_key_value_store.py
cloud_pipelines/components/_naming.py
cloud_pipelines/components/_python_op.py
cloud_pipelines/components/_python_to_graph_component.py
cloud_pipelines/components/_structures.py
cloud_pipelines/components/_yaml_utils.py
cloud_pipelines/components/modelbase.py
cloud_pipelines/components/structures/__init__.py
cloud_pipelines_components-0.22.4.25.dist-info/LICENSE
cloud_pipelines_components-0.22.4.25.dist-info/METADATA
cloud_pipelines_components-0.22.4.25.dist-info/WHEEL
cloud_pipelines_components-0.22.4.25.dist-info/top_level.txt
cloud_pipelines_components-0.22.4.25.dist-info/RECORD
