Metadata-Version: 2.1
Name: cloud-pipelines-components
Version: 0.22.4.25
Summary: SDK for building pipeline components for Cloud Pipelines
Home-page: https://github.com/Cloud-Pipelines/sdk-components
Author: Alexey Volkov
Author-email: alexey.volkov@ark-kun.com
License: Apache License 2.0
Project-URL: Bug Tracker, https://github.com/Cloud-Pipelines/sdk-components/issues
Project-URL: Website, https://cloud-pipelines.net
Platform: UNKNOWN
Classifier: Development Status :: 4 - Beta
Classifier: Intended Audience :: Developers
Classifier: Intended Audience :: Education
Classifier: Intended Audience :: Science/Research
Classifier: License :: OSI Approved :: Apache Software License
Classifier: Operating System :: OS Independent
Classifier: Programming Language :: Python :: 3
Classifier: Programming Language :: Python :: 3.7
Classifier: Programming Language :: Python :: 3.8
Classifier: Programming Language :: Python :: 3.9
Classifier: Programming Language :: Python :: 3.10
Classifier: Topic :: Scientific/Engineering
Classifier: Topic :: Scientific/Engineering :: Artificial Intelligence
Requires-Python: >=3.7
License-File: LICENSE
Requires-Dist: docstring-parser
Requires-Dist: requests
Requires-Dist: strip-hints (>=0.1.8)
Provides-Extra: tests
Requires-Dist: mock ; extra == 'tests'
